<?xml version="1.0" encoding="UTF-8"?>
<!DOCTYPE dmodule PUBLIC "-//S1000D//DTD Data Module//EN" "dm.dtd">
<!-- 
S1000D Data Module: Wing Structure General Description
Data Module Code: DMC-BWB-Q100-A-57-10-00-00A-040A-D-EN-US
System: ATA-57 Wings
Subsystem: 57-10 Wing Structure General
Information Type: 040 - Description
-->
<dmodule>
  <identAndStatusSection>
    <dmAddress>
      <dmIdent>
        <dmCode modelIdentCode="BWB-Q100" systemDiffCode="A" systemCode="57" 
                subSystemCode="10" subSubSystemCode="00" assyCode="00" 
                disassyCode="00A" disassyCodeVariant="A" infoCode="040" 
                infoCodeVariant="A" itemLocationCode="D"/>
        <language languageIsoCode="en" countryIsoCode="US"/>
        <issueInfo issueNumber="001" inWork="00"/>
      </dmIdent>
      <dmAddressItems>
        <issueDate year="2025" month="01" day="22"/>
        <dmTitle>
          <techName>Wing Structure</techName>
          <infoName>General Description</infoName>
        </dmTitle>
      </dmAddressItems>
    </dmAddress>
    <dmStatus issueType="new">
      <security securityClassification="01"/>
      <dataRestrictions>
        <restrictionInfo>
          <restrictionInstructions>INTERNAL-EVIDENCE-REQUIRED</restrictionInstructions>
        </restrictionInfo>
      </dataRestrictions>
      <responsiblePartnerCompany>
        <enterpriseName>ASI-T2 Architecture Team</enterpriseName>
      </responsiblePartnerCompany>
      <originator>
        <enterpriseName>AMPEL360 BWB-Q100 Program</enterpriseName>
      </originator>
      <applic>
        <displayText>
          <simplePara>BWB-Q100 Baseline Configuration (conf_000_baseline), MSN 0001-9999</simplePara>
        </displayText>
      </applic>
      <brexDmRef>
        <dmRef>
          <dmRefIdent>
            <dmCode modelIdentCode="S1000D" systemDiffCode="F" systemCode="04" 
                    subSystemCode="10" subSubSystemCode="00" assyCode="00" 
                    disassyCode="00A" disassyCodeVariant="A" infoCode="022" 
                    infoCodeVariant="A" itemLocationCode="D"/>
          </dmRefIdent>
        </dmRef>
      </brexDmRef>
      <qualityAssurance>
        <unverified/>
      </qualityAssurance>
    </dmStatus>
  </identAndStatusSection>
  
  <content>
    <description>
      <levelledPara>
        <title>General</title>
        <para>
          The BWB-Q100 wing structure represents an advanced blended wing body configuration 
          optimized for transport civil aviation applications. The wing system integrates 
          seamlessly with the center body to form a continuous lifting surface.
        </para>
      </levelledPara>
      
      <levelledPara>
        <title>Wing Box Primary Structure</title>
        <para>
          The wing box forms the primary structural element of the wing system, providing:
        </para>
        <randomList>
          <listItem>
            <para>Primary load paths for flight and ground loads</para>
          </listItem>
          <listItem>
            <para>Fuel containment structure for integral fuel tanks</para>
          </listItem>
          <listItem>
            <para>Mounting points for control surfaces and equipment</para>
          </listItem>
          <listItem>
            <para>Integration interface with center body structure</para>
          </listItem>
        </randomList>
      </levelledPara>
      
      <levelledPara>
        <title>Design Requirements</title>
        <para>
          The wing structure is designed to meet the following requirements:
        </para>
        <randomList>
          <listItem>
            <para>Ultimate load factors per CS-25 certification standards</para>
          </listItem>
          <listItem>
            <para>Fatigue life of ≥ 90,000 flight cycles</para>
          </listItem>
          <listItem>
            <para>Fail-safe design philosophy for damage tolerance</para>
          </listItem>
          <listItem>
            <para>CFRP primary structure with metallic/titanium fittings</para>
          </listItem>
        </randomList>
      </levelledPara>
      
      <levelledPara>
        <title>Integration with ASI-T2 Systems</title>
        <para>
          This data module integrates with ASI-T2 quantum-enhanced engineering processes:
        </para>
        <randomList>
          <listItem>
            <para>QS/UTCS: Quantum Seal / Universal Traceability Reference: [To be assigned]</para>
          </listItem>
          <listItem>
            <para>CAx Integration: Classical analysis results from ../../cax/CAE/wing_structural_analysis/</para>
          </listItem>
          <listItem>
            <para>QOx Integration: Quantum optimization results from ../../qox/CAE/runs/20250122-load_path_opt/</para>
          </listItem>
          <listItem>
            <para>SIM Metrics: Weight reduction -12%, Material waste -15% vs baseline</para>
          </listItem>
        </randomList>
      </levelledPara>
    </description>
  </content>
</dmodule>